Metadata-Version: 1.1
Name: file-structure-generator
Version: 0.0.7
Summary: A folder structure generator tool.
Home-page: https://github.com/mjalas/file-structure-generator
Author: Mats Jalas
Author-email: mats.jalas@gmail.com
License: MIT
Keywords: folder-generator
Platform: UNKNOWN
Classifier: Development Status :: 3 - Alpha
Classifier: Intended Audience :: Developers
Classifier: Topic :: Software Development :: Libraries
Classifier: License :: OSI Approved :: MIT License
Classifier: Programming Language :: Python :: 3.4
Classifier: Programming Language :: Python :: 3.5
